partialwrap/__init__.py
partialwrap/_version.py
partialwrap/std_io.py
partialwrap/wrappers.py
partialwrap-2.0.dist-info/AUTHORS.rst
partialwrap-2.0.dist-info/LICENSE
partialwrap-2.0.dist-info/METADATA
partialwrap-2.0.dist-info/WHEEL
partialwrap-2.0.dist-info/top_level.txt
partialwrap-2.0.dist-info/RECORD
